{"singlePage": [], "startSite": "", "filingNum": "", "onePageListNum": 15, "commentLabelColor": "#006b75", "yearColorList": ["#bc4c00", "#0969da", "#1f883d", "#A333D0"], "i18n": "CN", "themeMode": "manual", "dayTheme": "light", "nightTheme": "dark", "urlMode": "pinyin", "script": "", "style": "", "head": "", "indexScript": "", "indexStyle": "", "bottomText": "", "showPostSource": 1, "iconList": {}, "UTC": 8, "rssSplit": "sentence", "exlink": {}, "needComment": 1, "allHead": "", "title": "\u571f\u62e8\u9f20\u7684\u535a\u5ba2", "subTitle": "\u8fd9\u91cc\u662f\u571f\u62e8\u9f20\u7684\u535a\u5ba2\uff0c\u7528\u6765\u6536\u96c6\u548c\u5206\u4eab\u6709\u8da3\u7684\u4e8b\u60c5", "avatarUrl": "https://easyimage.01011205.xyz/i/2024/09/08/nlnmn5.png", "GMEEK_VERSION": "last", "postListJson": {"P1": {"htmlDir": "docs/post/tu-bo-shu-de-wo.html", "labels": ["documentation"], "postTitle": "\u571f\u62e8\u9f20\u7684\u7a9d", "postUrl": "post/tu-bo-shu-de-wo.html", "postSourceUrl": "https://github.com/samling-jackyjyo/samling-jackyjyo.github.io/issues/1", "commentNum": 0, "wordCount": 9, "description": "\u6536\u85cf\u5404\u79cd\u6709\u8da3\u7684\u5de5\u5177\u3002", "top": 0, "createdAt": 1725347907, "style": "", "script": "", "head": "", "ogImage": "https://easyimage.01011205.xyz/i/2024/09/08/nlnmn5.png", "createdDate": "2024-09-03", "dateLabelColor": "#bc4c00"}, "P2": {"htmlDir": "docs/post/li-yong-cloudflarework+pages-bu-shu-yi-ge-jian-yi-de-lin-shi-you-jian-xi-tong--cloudflare-yang-mao-xi-lie.html", "labels": ["documentation"], "postTitle": "\u5229\u7528cloudflarework+pages\u90e8\u7f72\u4e00\u4e2a\u7b80\u6613\u7684\u4e34\u65f6\u90ae\u4ef6\u7cfb\u7edf-cloudflare\u7f8a\u6bdb\u7cfb\u5217", "postUrl": "post/li-yong-cloudflarework%2Bpages-bu-shu-yi-ge-jian-yi-de-lin-shi-you-jian-xi-tong--cloudflare-yang-mao-xi-lie.html", "postSourceUrl": "https://github.com/samling-jackyjyo/samling-jackyjyo.github.io/issues/2", "commentNum": 0, "wordCount": 4004, "description": "# \u9879\u76ee\u5b98\u65b9\u6587\u6863\r\n\r\n[https://temp-mail-docs.awsl.uk/zh/guide/config-send-mail](https://temp-mail-docs.awsl.uk/zh/guide/config-send-mail)\r\n\r\n# \u9879\u76eegithub\u4ed3\u5e93\r\n\r\n[https://github.com/dreamhunter2333/cloudflare_temp_email](https://github.com/dreamhunter2333/cloudflare_temp_email)\r\n\r\n# \u5b89\u88c5\u8fc7\u7a0b\r\n\r\n## \u9996\u5148\u8981\u5b9a\u4e49\u4e24\u4e2a\u57df\u540d\r\n\r\n- \u524d\u7aefurl webmail.0808888.xyz\r\n- \u540e\u7aefurl cfmail-api.0808888.xyz\r\n\r\n## 1.\u6570\u636e\u5e93\u8bbe\u7f6e\r\n\r\n- \u5728works\u548cpages\u4e2d\u9009D1\u6570\u636e\u5e93\r\n- \u521b\u5efa\u6570\u636e\u5e93\u8d77\u540d\u5b57dev\r\n- \u521b\u5efa\u540e\u8fdb\u5165\u5230dev\u6570\u636e\u5e93,\u7136\u540e\u6253\u5f00consol\u6807\u7b7e  \r\n    -\u628a\u00a0[https://github.com/dreamhunter2333/cloudflare_temp_email/blob/main/db/schema.sql](https://github.com/dreamhunter2333/cloudflare_temp_email/blob/main/db/schema.sql)\u8fd9\u4e2aschema.sql\u6587\u4ef6\u4e2d\u7684\u5185\u5bb9\u590d\u5236\u5230donsol\u4e2d,\u7136\u540e\u70b9\u51fbExecute\u6309\u94ae\r\n- \u6570\u636e\u5e93\u521b\u5efa\u5b8c\u6210\r\n\r\n---\r\n\r\n## 2.\u540e\u53f0\u7a0b\u5e8f\u90e8\u7f72\r\n\r\n- \u8fd8\u662f\u5728\u5728works\u548cpages\u4e2d,\u521b\u5efa\u5e94\u7528\u7a0b\u5e8f,\u9009workers\r\n- \u8d77\u540d\u5b57cfmail-api,\u4fdd\u5b58,\u7136\u540e\u70b9\u53f3\u4e0b\u89d2\u5b8c\u6210.\r\n- \u7136\u540e\u754c\u9762\u4e2d\u53f3\u4e0a\u89d2\u70b9edit code.\r\n- \u7136\u540e\u518d\u5de6\u8fb9\u70b9\u51fb\u6587\u4ef6\u6309\u94ae,\u53f3\u952e\u70b9works.js\u7136\u540e\u5220\u9664.\r\n- **\u518d\u4e0b\u8f7d[works.js](https://github.com/dreamhunter2333/cloudflare_temp_email/releases/latest/download/worker.js)**\r\n- \u53f3\u952e\u70b9\u51fb,\u51fa\u73b0\u4e0a\u4f20,\u628a\u4e0b\u8f7d\u7684works.js\u4e0a\u4f20\u4e0a\u53bb,\u7136\u540e\u53f3\u4e0a\u89d2\u90e8\u7f72\r\n- \u518d\u6765\u5230\u9879\u76ee\u7684settings-->Variables\u4e2d,\u6dfb\u52a0\u53d8\u91cf\r\n- \u5f00\u59cb\u90e8\u7f72\u65f6\u6211\u4eec\u53ea\u6dfb\u52a04\u4e2a\u53d8\u91cf,\u6587\u7ae0\u7ed3\u5c3e\u6211\u9644\u5e26\u4e86\u53ef\u8bbe\u7f6e\u7684\u53d8\u91cf\u4ee3\u7801\u793a\u4f8b\u8bf4\u660e.\r\n    \r\n    - ADMIN_PASSWORDS = ['1234']\r\n    - PASSWORDS = ['1234']\r\n    - DOMAINS = ['milaone.app']\r\n    - JWT_SECRET =['xxxyyyzzz']\r\n- \u5728KV Namespace Bindings\u4e2d\u6dfb\u52a0\u4e00\u4e2aKV\r\n    \r\n    - \u521b\u5efa\u4e00\u4e2aKV,\u8d77\u540d\u5b57dev\r\n    - \u7136\u540e\u5728\u8fd9\u91ccVariable name\u586b KV \u5927\u5199.\r\n    - KV Namespace\u9009\u62e9\u521b\u5efa\u7684KV\u5e93dev\r\n- \u6dfb\u52a0D1\u6570\u636e\u5e93\r\n    \r\n    - \u540c\u6837\u5728settings-->Variable\u4e2d,\u627e\u5230D1 Database,\u6dfb\u52a0\u4e0a\u4e00\u6b65\u521b\u5efa\u7684\u6570\u636e\u5e93dev\r\n- \u6700\u540e\u518d\u8fdb\u884c\u90e8\u7f72\u4e00\u6b21.\r\n\r\n- \u540e\u7aef\u9a8c\u8bc1\r\n    \r\n    - \u540e\u7aef\u8bbe\u7f6e\u5b8c\u6210\u540e,\u53ef\u4ee5\u901a\u8fc7\u8bbf\u95ee\u540e\u7aef\u57df\u540d\u7684url\u53ca\u76ee\u5f55\u8fdb\u884c\u9a8c\u8bc1,\u4f8b\u5982\u6211\u7684\u57df\u540d\r\n    - cfmail-api.0808888.xyz \u8fd4\u56de\u7ed3\u679cOK\r\n    - cfmail-api.0808888.xyz/health_check \u8fd4\u56de\u7ed3\u679cOK\r\n    - \u5219\u8bf4\u660e\u540e\u7aef\u914d\u7f6e\u5b8c\u6210.\u540e\u671f\u53ef\u968f\u65f6\u5728\u53d8\u91cf\u4e2d\u589e\u5220\u5185\u5bb9\u4ee5\u8fbe\u5230\u914d\u7f6e\u6548\u679c\r\n\r\n---\r\n\r\n## 3.\u524d\u53f0\u7a0b\u5e8f\u90e8\u7f72\r\n\r\n- \u8fd8\u662f\u5728\u5728works\u548cpages\u4e2d,\u521b\u5efa\u5e94\u7528\u7a0b\u5e8f,\u9009Pages\r\n- \u9009\u62e9Create using direct upload,\u7136\u540e\u518d\u9009\u62e9Upload assets\u6309\u94ae\r\n- \u7136\u540e\u6765\u5230\u4f5c\u8005\u7684\u5b98\u65b9\u6587\u6863\u4e2d\u00a0[\u70b9\u51fb\u8fd9\u91cc\u751f\u6210\u914d\u7f6e\u6587\u4ef6](https://temp-mail-docs.awsl.uk/zh/guide/ui/pages.html)\r\n- \u5728\u8be5\u9875\u9762\u4e2d\u7684\u5730\u5740\u680f\u8f93\u5165\u540e\u7aef\u7684\u57df\u540d\u7684https\u5730\u5740,\u6bd4\u5982\u6211\u4f7f\u7528\u7684\u5730\u5740\u662f[https://cfmail-api.0808888.xyz](https://cfmail-api.0808888.xyz/)\u00a0\u751f\u6210\u914d\u7f6e,\u5f97\u5230\u4e0b\u8f7d\u4e00\u4e2afrontend.zip\u6587\u4ef6,\u4e0a\u4f20\u5230pages\u4e2d.  \r\n    ![2024-06-06T02:47:55.png](https://www.milaone.com/usr/uploads/2024/06/1764034871.png '2024-06-06T02:47:55.png')\r\n- \u6700\u540e\u5728Custom Domain\u7ed9\u524d\u7aef\u81ea\u5b9a\u4e49\u4e00\u4e2a\u57df\u540d,\u4f8b\u5982\u6211\u4f7f\u7528\u7684\u662fwebmail.0808888.xyz\r\n- \u524d\u7aef\u9a8c\u8bc1,\u8bbf\u95ee\u524d\u7aef[https://webmail.milaone.com](https://webmail.milaone.com/),\u6b64\u65f6\u5e94\u8be5\u51fa\u73b0\u754c\u9762\u5e76\u63d0\u793a\u8f93\u5165\u5bc6\u7801\r\n\r\n## 3.\u90ae\u4ef6\u8def\u7531\u8bbe\u7f6e\r\n\r\n- \u6765\u5230[https://dash.cloudflare.com](https://dash.cloudflare.com/)\u00a0\u9762\u677f\u9996\u9875,\u7136\u540e\u9009\u62e9\u9700\u8981\u4f7f\u7528\u7684\u57df\u540d\u8fdb\u5165.\r\n- \u5de6\u8fb9\u9009\u62e9Email\u83dc\u5355,\u5728Email Routing\u4e2d\u9009\u62e9Routing ruls\u4e2dCatch-all address  \r\n    \u6fc0\u6d3b,\u5e76\u4e14edit.\r\n- \u5176\u4e2d\u7684Action\u9009\u62e9\u7684\u662fSend to a Worker ,\u76ee\u6807\u9009\u62e9\u540e\u7aef\u7684worker\u540d\u5b57\r\n- \u9a8c\u8bc1:\u622a\u6b62\u5230\u73b0\u5728\u767b\u5f55\u524d\u7aefurl\u5df2\u7ecf\u53ef\u4ee5\r\n\r\n## 4.\u53d1\u9001\u90ae\u4ef6\u8bbe\u7f6e\r\n\r\n- [https://resend.com/domains](https://resend.com/domains)\u8fdb\u884c\u57df\u540d\u9a8c\u8bc1\r\n- \u7136\u540e\u5728API-Key \u4e2d\u521b\u5efa\u4e00\u4e2aapi,\u5168\u90e8\u6743\u9650,\u7136\u540e\u628a\u5bc6\u7801\u62f7\u8d1d\r\n- \u5230\u540e\u7aef\u7684Worker\u4e2dSettings-->Environment Variables-->\u6dfb\u52a0\u4e00\u4e2a\u53d8\u91cf\r\n- RESEND_TOKEN = re_PxW46o6o_HJrmMYARCGdhMtB3JHD(\u4e0a\u4e00\u6b65\u62f7\u8d1d\u51fa\u6765\u7684\u5bc6\u7801)\r\n\r\n## \u622a\u6b62\u5230\u4ee5\u4e0a\u6b65\u9aa4,\u5c31\u53ef\u4ee5\u5b8c\u6574\u7684\u6536\u53d1\u90ae\u4ef6\u4e86.\r\n\r\n## \u5982\u679c\u9700\u8981\u66f4\u65b9\u4fbf\u7684\u670b\u53cb,\u5f3a\u70c8\u5efa\u8bae\u6302\u4e0aTelegram\u673a\u5668\u4eba\r\n\r\n## 5.Telegram\u673a\u5668\u4eba\r\n\r\n- \u521b\u5efa\u673a\u5668\u4eba(\u5177\u4f53\u65b9\u6cd5\u81ea\u5df1\u641c.)\r\n- \u62ff\u5230\u7528\u4e8e\u8fd9\u4e2a\u9879\u76ee\u7684\u673a\u5668\u4ebatoken,\u8fd8\u6709telegram\u7684\u8d26\u6237id.\r\n- \u5230\u540e\u7aef\u7684Worker\u4e2dSettings-->Environment Variables-->\u6dfb\u52a0\u4e00\u4e2a\u53d8\u91cf\r\n- TELEGRAM_BOT_TOKEN = \u673a\u5668\u4ebatoken\r\n- \u5728\u90ae\u4ef6\u7684\u7ba1\u7406\u540e\u53f0,\u673a\u5668\u4eba\u4e2d\u586b\u5165\u8d26\u6237id.\r\n\r\n# \u96441:\u53d8\u91cf\u8bf4\u660e\r\n\r\n```\r\n[vars]\r\n# TITLE = 'Custom Title' # \u81ea\u5b9a\u4e49\u7f51\u7ad9\u6807\u9898\r\nPREFIX = 'tmp' # \u8981\u5904\u7406\u7684\u90ae\u7bb1\u540d\u79f0\u524d\u7f00\uff0c\u4e0d\u9700\u8981\u540e\u7f00\u53ef\u914d\u7f6e\u4e3a\u7a7a\u5b57\u7b26\u4e32\r\n# \u5982\u679c\u4f60\u60f3\u8981\u4f60\u7684\u7f51\u7ad9\u79c1\u6709\uff0c\u53d6\u6d88\u4e0b\u9762\u7684\u6ce8\u91ca\uff0c\u5e76\u4fee\u6539\u5bc6\u7801\r\n# PASSWORDS = ['123', '456']\r\n# admin \u63a7\u5236\u53f0\u5bc6\u7801, \u4e0d\u914d\u7f6e\u5219\u4e0d\u5141\u8bb8\u8bbf\u95ee\u63a7\u5236\u53f0\r\n# ADMIN_PASSWORDS = ['123', '456']\r\n# admin \u8054\u7cfb\u65b9\u5f0f\uff0c\u4e0d\u914d\u7f6e\u5219\u4e0d\u663e\u793a\uff0c\u53ef\u914d\u7f6e\u4efb\u610f\u5b57\u7b26\u4e32\r\n# ADMIN_CONTACT = 'xx@xx.xxx'\r\nDOMAINS = ['xxx.xxx1' , 'xxx.xxx2'] # \u4f60\u7684\u57df\u540d, \u652f\u6301\u591a\u4e2a\u57df\u540d\r\nJWT_SECRET = 'xxx' # \u7528\u4e8e\u751f\u6210 jwt \u7684\u5bc6\u94a5, jwt \u7528\u4e8e\u7ed9\u7528\u6237\u767b\u5f55\u4ee5\u53ca\u9274\u6743\r\nBLACK_LIST = '' # \u9ed1\u540d\u5355\uff0c\u7528\u4e8e\u8fc7\u6ee4\u53d1\u4ef6\u4eba\uff0c\u9017\u53f7\u5206\u9694\r\n# \u662f\u5426\u5141\u8bb8\u7528\u6237\u521b\u5efa\u90ae\u4ef6, \u4e0d\u914d\u7f6e\u5219\u4e0d\u5141\u8bb8\r\nENABLE_USER_CREATE_EMAIL = true\r\n# \u5141\u8bb8\u7528\u6237\u5220\u9664\u90ae\u4ef6, \u4e0d\u914d\u7f6e\u5219\u4e0d\u5141\u8bb8\r\nENABLE_USER_DELETE_EMAIL = true\r\n# \u5141\u8bb8\u81ea\u52a8\u56de\u590d\u90ae\u4ef6\r\nENABLE_AUTO_REPLY = false\r\n# \u662f\u5426\u542f\u7528 webhook\r\n# ENABLE_WEBHOOK = true\r\n# \u524d\u7aef\u754c\u9762\u9875\u811a\u6587\u672c\r\n# COPYRIGHT = 'Dream Hunter'\r\n# \u9ed8\u8ba4\u53d1\u9001\u90ae\u4ef6\u4f59\u989d\uff0c\u5982\u679c\u4e0d\u8bbe\u7f6e\uff0c\u5c06\u4e3a 0\r\n# DEFAULT_SEND_BALANCE = 1\r\n# Turnstile \u4eba\u673a\u9a8c\u8bc1\u914d\u7f6e\r\n# CF_TURNSTILE_SITE_KEY = ''\r\n# CF_TURNSTILE_SECRET_KEY = ''\r\n# dkim config\r\n# DKIM_SELECTOR = 'mailchannels' # \u53c2\u8003 DKIM \u90e8\u5206 mailchannels._domainkey \u7684 mailchannels\r\n# DKIM_PRIVATE_KEY = '' # \u53c2\u8003 DKIM \u90e8\u5206 priv_key.txt \u7684\u5185\u5bb9\r\n# telegram bot \u6700\u591a\u7ed1\u5b9a\u90ae\u7bb1\u6570\u91cf\r\n# TG_MAX_ACCOUNTS = 5\r\n# \u5168\u5c40\u8f6c\u53d1\u5730\u5740\u5217\u8868\uff0c\u5982\u679c\u4e0d\u914d\u7f6e\u5219\u4e0d\u542f\u7528\uff0c\u542f\u7528\u540e\u6240\u6709\u90ae\u4ef6\u90fd\u4f1a\u8f6c\u53d1\u5230\u5217\u8868\u4e2d\u7684\u5730\u5740\r\n# FORWARD_ADDRESS_LIST = ['xxx@xxx.com']\u3002", "top": 0, "createdAt": 1725362130, "style": "", "script": "", "head": "", "ogImage": "https://easyimage.01011205.xyz/i/2024/09/08/nlnmn5.png", "createdDate": "2024-09-03", "dateLabelColor": "#bc4c00"}, "P3": {"htmlDir": "docs/post/yong-poste.io-da-jian-you-ju-jiao-cheng.html", "labels": ["documentation"], "postTitle": "\u7528poste.io\u642d\u5efa\u90ae\u5c40\u6559\u7a0b", "postUrl": "post/yong-poste.io-da-jian-you-ju-jiao-cheng.html", "postSourceUrl": "https://github.com/samling-jackyjyo/samling-jackyjyo.github.io/issues/3", "commentNum": 0, "wordCount": 2968, "description": "## \u4e00.\u642d\u5efa\u524d\u7684\u51c6\u5907\r\n\r\n1\u3001\u57df\u540d\u4e00\u4e2a\uff0c\u5982\u679c\u6ca1\u6709\uff0c\u8d2d\u4e70\u4e00\u4e2acom\u3001net\u6216\u8005org\uff0c\u4e0d\u63a8\u8350\u7528\u4e0d\u53d7\u4fe1\u4efb\u7684\u57df\u540d\u540e\u7f00\u3002", "top": 0, "createdAt": 1725364439, "style": "", "script": "", "head": "", "ogImage": "https://easyimage.01011205.xyz/i/2024/09/08/nlnmn5.png", "createdDate": "2024-09-03", "dateLabelColor": "#bc4c00"}, "P5": {"htmlDir": "docs/post/da-jian-duo-gong-neng-de-kai-yuan-huan-jing-gong-ju-1panel.html", "labels": ["documentation"], "postTitle": "\u642d\u5efa\u591a\u529f\u80fd\u7684\u5f00\u6e90\u73af\u5883\u5de5\u51771panel", "postUrl": "post/da-jian-duo-gong-neng-de-kai-yuan-huan-jing-gong-ju-1panel.html", "postSourceUrl": "https://github.com/samling-jackyjyo/samling-jackyjyo.github.io/issues/5", "commentNum": 0, "wordCount": 1446, "description": "![0bf209eb28da82a04aa1a.jpg](https://img.yohaman.pp.ua/file/0bf209eb28da82a04aa1a.jpg)\r\n[\u8f6c\u8f7d\uff1a\u4e00\u74f6\u5976\u6cb91Panel\u642d\u5efaWordpress](https://naiyous.com/5690.html)\r\n\r\n\u51c6\u5907\u5de5\u4f5c\r\n\r\n\u4e0b\u8f7d\u5e76\u5b89\u88c5SSH\u8fde\u63a5\u5de5\u5177Finalshell\uff1a\u3010[\u70b9\u51fb\u8fdb\u5165](https://www.hostbuf.com/t/988.html)\u3011\r\n\r\n\u51c6\u5907\u4e00\u4e2a\u57df\u540d\u5e76\u6258\u7ba1\u5230Cloudflare\uff1a\u3010[\u70b9\u51fb\u8fdb\u5165](https://dash.cloudflare.com/login)\u3011\r\n\r\n1\u3001\u5173\u95ed\u9632\u706b\u5899/\u8bbe\u7f6e\u9632\u706b\u5899\u89c4\u5219\r\n\r\nufw disable\r\n2\u3001\u66f4\u65b0\u7cfb\u7edf\r\n\r\napt update -y  && apt upgrade -y\r\n3\u30011Panel\u5b98\u7f51\uff1a\u3010[\u70b9\u51fb\u8fdb\u5165](https://1panel.cn/)\u3011\r\n\r\n\u4e00\u952e\u5b89\u88c5\u811a\u672c\r\ncurl -sSL https://resource.fit2cloud.com/1panel/package/quick_start.sh -o quick_start.sh && sudo bash quick_start.sh\r\n4\u3001\u5b89\u88c5\u5e94\u7528\uff1aOpenResty\u3001MySQL\u3001Redis\u3001PHP8\r\n\r\n5\u3001\u521b\u5efa\u6570\u636e\u5e93\r\n\r\n\u70b9\u51fb\u521b\u5efa\u6570\u636e\u5e93\u2014\u2014\u81ea\u5b9a\u4e49\u540d\u79f0\u548c\u7528\u6237\u540d\u2014\u2014\u5bc6\u7801\u968f\u673a\u2014\u2014\u5176\u5b83\u4fdd\u6301\u9ed8\u8ba4\u2014\u2014\u70b9\u51fb\u786e\u5b9a\r\n6\u3001\u521b\u5efa\u7f51\u7ad9\u5e76\u7533\u8bf7\u8bc1\u4e66\r\n\r\n\u70b9\u51fb\u521b\u5efa\u7f51\u7ad9\u2014\u2014\u70b9\u51fb\u8fd0\u884c\u73af\u5883\u2014\u2014\u5176\u5b83\u4fdd\u6301\u9ed8\u8ba4\u2014\u2014\u8f93\u5165\u89e3\u6790\u597d\u7684\u57df\u540d\u2014\u2014\u70b9\u51fb\u786e\u5b9a\r\n\r\n\u70b9\u51fb\u8bc1\u4e66\u2014\u2014\u70b9\u51fbAcme\u8d26\u6237\u2014\u2014\u70b9\u51fb\u521b\u5efa\u8d26\u6237\u2014\u2014\u8f93\u5165\u90ae\u7bb1\uff08==\u4f60\u81ea\u5df1\u7684\u90ae\u7bb1==\uff09\u2014\u2014\u70b9\u51fb\u786e\u5b9a\u2014\u2014\u70b9\u51fb\u8fd4\u56de\u2014\u2014\u70b9\u51fb\u7533\u8bf7\u8bc1\u4e66\u2014\u2014\u8f93\u5165\u89e3\u6790\u597d\u7684\u57df\u540d\u2014\u2014\u5176\u5b83\u4fdd\u6301\u4e0d\u53d8\u2014\u2014\u9a8c\u8bc1\u65b9\u5f0f\u9009\u62e9HTTP\u2014\u2014\u70b9\u51fb\u786e\u5b9a\uff08==\u6ce8\u610f\uff1a\u8fd9\u4e00\u6b65\u7533\u8bf7\u8bc1\u4e66\u524d\uff0c\u8bf7\u68c0\u67e5\u9632\u706b\u5899\u662f\u5426\u5173\u95ed\u6216\u8005\u653e\u884c80\u7aef\u53e3==\uff09\r\n\r\n\u70b9\u51fb\u7f51\u7ad9\u2014\u2014\u70b9\u51fb\u7f51\u7ad9\u540d\u79f0\u2014\u2014\u70b9\u51fbHTTPS\u2014\u2014\u542f\u7528 HTTPS\u2014\u2014Acme \u8d26\u6237\u70b9\u5f00\u2014\u2014\u9009\u62e9\u524d\u9762\u521b\u5efa\u597d\u7684\u8d26\u6237\u2014\u2014\u70b9\u51fb\u4fdd\u5b58\r\n\r\n\u70b9\u51fb\u7f51\u7ad9\u76ee\u5f55\u2014\u2014\u70b9\u51fb\u201croot\u76ee\u5f55\u201d\u540e\u9762\u7684\u84dd\u8272\u6587\u4ef6\u5939\u56fe\u6807\u2014\u2014\u628aindex.php\u6587\u4ef6\u5220\u6389\u2014\u2014\u70b9\u51fb\u8fdc\u7a0b\u4e0b\u8f7d\u2014\u2014Wordpress\u4e0b\u8f7d\uff1a\u3010[\u70b9\u51fb\u8fdb\u5165](https://cn.wordpress.org/download/)\u3011\u2014\u2014\u590d\u5236\u94fe\u63a5\u5730\u5740\u8fc7\u6765\u2014\u2014\u70b9\u51fb\u786e\u8ba4\u2014\u2014\u4e0b\u8f7d\u5b8c\u6210\u540e\u5173\u6389\u2014\u2014\u89e3\u538b\u4e0b\u8f7d\u7684\u6587\u4ef6\u2014\u2014\u70b9\u51fb\u786e\u8ba4\u2014\u2014\u5f97\u5230wordpress\u6587\u4ef6\u5939\u2014\u2014\u628a\u538b\u7f29\u5305\u5220\u9664\u2014\u2014\u518d\u70b9\u51fb\u5230\u7f51\u7ad9\u2014\u2014\u70b9\u51fb\u7f51\u7ad9\u540d\u79f0\u2014\u2014\u70b9\u51fb\u7f51\u7ad9\u76ee\u5f55\u2014\u2014\u70b9\u5f00\u8fd0\u884c\u76ee\u5f55\u2014\u2014\u9009\u62e9/wordpress\u2014\u2014\u70b9\u51fb\u4fdd\u5b58\u5e76\u91cd\u8f7d\r\n\r\n7\u3001Wordpress\u767b\u5f55\u5e76\u8bbe\u7f6e\r\n\r\n\u65b0\u6253\u5f00\u4e00\u4e2a\u9875\u9762\u2014\u2014\u8f93\u5165\u7f51\u7ad9\u57df\u540d\u2014\u2014\u70b9\u51fb\u73b0\u5728\u5c31\u5f00\u59cb\u2014\u2014\u56de\u52301panel\u9762\u677f\u2014\u2014\u70b9\u51fb\u6570\u636e\u5e93\u2014\u2014\u628a\u6570\u636e\u5e93\u540d\u79f0\u3001\u7528\u6237\u540d\u3001\u5bc6\u7801\u590d\u5236\u8fc7\u6765\u2014\u2014\u6570\u636e\u5e93\u4e3b\u673a\u8f93\u5165\uff1amysql\u2014\u2014\u70b9\u51fb\u4e0b\u4e00\u6b65\u2014\u2014\u590d\u5236\u914d\u7f6e\u6587\u4ef6\u5185\u5bb9\u2014\u2014\u56de\u52301panel\u9762\u677f\u2014\u2014\u70b9\u51fb\u7f51\u7ad9\u2014\u2014\u70b9\u51fb\u7f51\u7ad9\u76ee\u5f55\u2014\u2014\u6253\u5f00wordpress\u2014\u2014\u627e\u5230\u6b64\u201cwp-config-sample.php\u201d\u5e76\u6253\u5f00\u2014\u2014\u5220\u9664\u91cc\u9762\u7684\u5185\u5bb9\u2014\u2014\u628a\u590d\u5236\u7684\u5185\u5bb9\u7c98\u8d34\u8fdb\u53bb\u2014\u2014\u70b9\u51fb\u786e\u8ba4\u2014\u2014\u518d\u628a\u6587\u4ef6\u91cd\u547d\u540d\u4e3a\u201cwp-config.php\u201d\u2014\u2014\u518d\u56de\u5230\u524d\u7aef\u2014\u2014\u70b9\u51fb\u8fd0\u884c\u5b89\u88c5\u7a0b\u5e8f\u2014\u2014\u7ad9\u70b9\u6807\u9898\u81ea\u5b9a\u4e49\u2014\u2014\u7528\u6237\u540d\u81ea\u5b9a\u4e49\u2014\u2014\u5bc6\u7801\u81ea\u5b9a\u4e49\u2014\u2014\u8f93\u5165\u81ea\u5df1\u7684\u90ae\u7bb1\u2014\u2014\u70b9\u51fb\u5b89\u88c5WordPress\u2014\u2014\u70b9\u51fb\u767b\u5f55\u2014\u2014\u8f93\u5165\u8bbe\u7f6e\u597d\u7684\u90ae\u7bb1\u548c\u5bc6\u7801\u2014\u2014\u5373\u53ef\u5b8c\u6210\u5b89\u88c5\u3002", "top": 0, "createdAt": 1725368107, "style": "", "script": "", "head": "", "ogImage": "https://easyimage.01011205.xyz/i/2024/09/08/nlnmn5.png", "createdDate": "2024-09-03", "dateLabelColor": "#bc4c00"}, "P6": {"htmlDir": "docs/post/Cloudflare Workers-you-xiu-xiang-mu-shou-ji.html", "labels": ["documentation"], "postTitle": "Cloudflare Workers\u4f18\u79c0\u9879\u76ee\u6536\u96c6", "postUrl": "post/Cloudflare%20Workers-you-xiu-xiang-mu-shou-ji.html", "postSourceUrl": "https://github.com/samling-jackyjyo/samling-jackyjyo.github.io/issues/6", "commentNum": 0, "wordCount": 13577, "description": "\u8f6c\u8f7d\u81ea\uff1a[Cloudflare Workers\u4f18\u79c0\u9879\u76ee\u6536\u96c6\uff08\u6301\u7eed\u66f4\u65b0\uff09 - iGdu (igdux.com)](https://www.igdux.com/workers)\r\n\r\n\r\nCloudflare \u662f\u4e00\u5bb6\u4f1f\u5927\u7684\u4e92\u8054\u7f51\u516c\u53f8\uff0c\u5979\u81f4\u529b\u4e8e\u5efa\u7acb\u66f4\u597d\u7684\u4e92\u8054\u7f51\u3002", "top": 0, "createdAt": 1725438886, "style": "", "script": "", "head": "", "ogImage": "https://easyimage.01011205.xyz/i/2024/09/08/nlnmn5.png", "createdDate": "2024-09-04", "dateLabelColor": "#bc4c00"}, "P7": {"htmlDir": "docs/post/Cloudflare-hao-yang-mao-xi-lie-zhi-duan-lian-jie-sheng-cheng-qi-fu-dai-tong-ji-tu-biao-fen-xi-gong-neng--Github-kai-yuan--pages-bu-shu--Cloudflare-yang-mao-xiao-zu-cheng-yuan---mian-fei-bu-shu---mian-VPS-xiang-mu.html", "labels": ["documentation"], "postTitle": "Cloudflare\u8585\u7f8a\u6bdb\u7cfb\u5217\u4e4b\u77ed\u94fe\u63a5\u751f\u6210\u5668\u9644\u5e26\u7edf\u8ba1\u56fe\u8868\u5206\u6790\u529f\u80fd|Github\u5f00\u6e90|pages\u90e8\u7f72|Cloudflare\u7f8a\u6bdb\u5c0f\u7ec4\u6210\u5458|\u514d\u8d39\u90e8\u7f72|\u514dVPS\u9879\u76ee", "postUrl": "post/Cloudflare-hao-yang-mao-xi-lie-zhi-duan-lian-jie-sheng-cheng-qi-fu-dai-tong-ji-tu-biao-fen-xi-gong-neng--Github-kai-yuan--pages-bu-shu--Cloudflare-yang-mao-xiao-zu-cheng-yuan---mian-fei-bu-shu---mian-VPS-xiang-mu.html", "postSourceUrl": "https://github.com/samling-jackyjyo/samling-jackyjyo.github.io/issues/7", "commentNum": 0, "wordCount": 1511, "description": "\u8f6c\u8f7d\u81ea\uff1a[Cloudflare\u8585\u7f8a\u6bdb\u7cfb\u5217\u4e4b\u77ed\u94fe\u63a5\u751f\u6210\u5668\u9644\u5e26\u7edf\u8ba1\u56fe\u8868\u5206\u6790\u529f\u80fd|Github\u5f00\u6e90|pages\u90e8\u7f72|Cloudflare\u7f8a\u6bdb\u5c0f\u7ec4\u6210\u5458|\u514d\u8d39\u90e8\u7f72|\u514dVPS\u9879\u76ee](https://www.youtube.com/watch?v=PaGkJVx-ZiA)\r\n\r\n## \u9879\u76ee\u7279\u70b9\r\n\u9996\u5148\uff0c\u8fd9\u4e2a\u9879\u76ee\u867d\u7136\u662f\u514d\u8d39\u7684\uff0c\u4f46\u529f\u80fd\u548c\u6027\u80fd\u90fd\u975e\u5e38\u51fa\u8272\u3002", "top": 0, "createdAt": 1725538485, "style": "", "script": "", "head": "", "ogImage": "https://easyimage.01011205.xyz/i/2024/09/08/nlnmn5.png", "createdDate": "2024-09-05", "dateLabelColor": "#bc4c00"}, "P8": {"htmlDir": "docs/post/GitHub-Models - -shi-yong-zhi-nan.html", "labels": ["documentation"], "postTitle": "GitHub-Models - \u4f7f\u7528\u6307\u5357", "postUrl": "post/GitHub-Models%20-%20-shi-yong-zhi-nan.html", "postSourceUrl": "https://github.com/samling-jackyjyo/samling-jackyjyo.github.io/issues/8", "commentNum": 0, "wordCount": 2484, "description": "\r\n## \u4e00\u3001GitHub Models\r\n\r\n[GitHub Models\u00a08](https://github.com/marketplace/models)\u00a0\u662f GitHub \u6700\u65b0\u63a8\u51fa\u7684\u6a21\u578b\u6258\u7ba1\u670d\u52a1\uff0c\u63d0\u4f9b\u514d\u8d39\u7684 AI \u6a21\u578b\u4f9b\u5f00\u53d1\u8005\u6d4b\u8bd5\u3002", "top": 0, "createdAt": 1725587485, "style": "", "script": "", "head": "", "ogImage": "https://easyimage.01011205.xyz/i/2024/09/08/nlnmn5.png", "createdDate": "2024-09-06", "dateLabelColor": "#bc4c00"}, "P9": {"htmlDir": "docs/post/zai- koyeb -shang-da-jian-yi-ge- WebSSH.html", "labels": ["documentation"], "postTitle": "\u5728 koyeb \u4e0a\u642d\u5efa\u4e00\u4e2a WebSSH", "postUrl": "post/zai-%20koyeb%20-shang-da-jian-yi-ge-%20WebSSH.html", "postSourceUrl": "https://github.com/samling-jackyjyo/samling-jackyjyo.github.io/issues/9", "commentNum": 0, "wordCount": 3290, "description": "\u81ea\u4ece WARP \u88ab\u5f3a\u4e86\u4ee5\u540e\uff0c\u6211\u4eec\u6ca1\u6709 IPV6 \u65e0\u6cd5\u8bbf\u95ee\u7eaf IPV6 \u5c0f\u9e21\uff0c\u8fd8\u6709\u5c31\u662f serv00 \u88ab\u5899\u4e86\u540e\u4e5f\u65e0\u6cd5\u901a\u8fc7 SSH \u8fde\u63a5\uff0c\u6240\u4ee5\u6211\u4eec\u90e8\u7f72\u4e00\u4e2a WebSSH \u89e3\u51b3\u8fd9\u4e9b\u95ee\u9898\u00a0![:wink:](https://linux.do/images/emoji/apple/wink.png?v=12 ':wink:')  \r\n\u5982\u56fe\uff1a\r\n![image.png](https://easyimage.01011205.xyz/i/0/2024/09/10/nujrzu-0.png)\r\n\r\n![](https://easyimage.01011205.xyz/i/0/2024/09/10/nutfjl-0.png)\r\n\r\n\r\n\u9879\u76ee\u5730\u5740\uff1a\r\n\r\n[github.com](https://github.com/crazypeace/huashengdun-webssh)\r\n![image.png](https://easyimage.01011205.xyz/i/0/2024/09/10/nvdwh0-0.png)\r\n\r\n\r\n### [GitHub - crazypeace/huashengdun-webssh: \u589e\u52a0\u751f\u6210 sshlink \u529f\u80fd\uff0c\u65b9\u4fbf\u6536\u85cf\uff0c\u4e0b\u6b21\u4f7f\u7528\u4e0d\u9700\u8981\u8f93\u5165\u5bc6\u7801\u3002", "top": 0, "createdAt": 1725951518, "style": "", "script": "", "head": "", "ogImage": "https://easyimage.01011205.xyz/i/2024/09/08/nlnmn5.png", "createdDate": "2024-09-10", "dateLabelColor": "#bc4c00"}, "P10": {"htmlDir": "docs/post/\u3010-tu-wen-jiao-cheng-\u3011-jia-kuan-shi-zhan-hui-jia-pian.html", "labels": ["documentation"], "postTitle": "\u3010\u56fe\u6587\u6559\u7a0b\u3011\u5bb6\u5bdb\u5b9e\u6218\u56de\u5bb6\u7bc7", "postUrl": "post/%E3%80%90-tu-wen-jiao-cheng-%E3%80%91-jia-kuan-shi-zhan-hui-jia-pian.html", "postSourceUrl": "https://github.com/samling-jackyjyo/samling-jackyjyo.github.io/issues/10", "commentNum": 0, "wordCount": 2533, "description": "### \u524d\u7f6e\u6761\u4ef6:\r\n\r\n\u4e00: iStoreOS\u8f6f\u8def\u7531\u4e00\u53f0(\u4e3b\u8def\u7531/\u65c1\u8def\u7531/\u5149\u732b\u6865\u63a5/\u975e\u5149\u732b\u6865\u63a5\u90fd\u65e0\u6240\u8c13)  \r\n\u4e8c: iStoreOS\u8f6f\u8def\u7531\u6709docker\u73af\u5883(\u4e00\u822c\u4f1a\u81ea\u5e26\u6709)\r\n\r\n### \u539f\u7406:\r\n\r\n\u6559\u7a0b\u5206\u4e3a\u4e24\u90e8\u4efd  \r\n1.iStoreOS\u5b89\u88c5Lucky'STUN\u5185\u7f51\u7a7f\u900f'\u83b7\u53d6\u516c\u7f51IP+\u7aef\u53e3  \r\n2.\u642d\u5efa\u8bbe'WireGuard'\u670d\u52a1\u5668  \r\n\u5b9e\u73b0\u56de\u5bb6!\r\n\r\n## \u6559\u7a0b\u5f00\u59cb:\r\n\r\n\u5148\u5728iStore\u91cc\u9762\u5b89\u88c5Lucky  \r\n\r\n![image.png](https://easyimage.01011205.xyz/i/0/2024/09/10/xep6vl-0.png)\r\n\r\n\u518d\u5b89\u88c5WireGuard  \r\n![image.png](https://easyimage.01011205.xyz/i/0/2024/09/10/xev9z1-0.png)\r\n\r\n\u4f7f\u7528iStoreOS\u9996\u9875'\u7ec8\u7aef'  \r\n![image.png](https://easyimage.01011205.xyz/i/0/2024/09/10/xexgm1-0.png)\r\n\r\n\u767b\u9646\u8d26\u53f7root \u5bc6\u7801\u8f6f\u8def\u7531\u7684\u5bc6\u7801(\u6ce8\u610f:\u8f93\u5165\u65f6\u4e0d\u4f1a\u663e\u793a,\u8f93\u597d\u540e\u6309\u56de\u8f66\u5373\u53ef)\r\n\r\n\ud83d\udc47\u590d\u5236\u8fd9\u4e2a\u4e0b\u9762\u8fd9\u4e9b\u4ee3\u7801\u8fdb\u53bb\u56de\u8f66\ud83d\udc47\u5c31\u80fd\u5b89\u88c5WireGuard\r\n\r\n```bash\r\ndocker run -d --name=wg-easy -e WG_HOST=123.123.123.123 -e PASSWORD=passwd123 -e WG_DEFAULT_ADDRESS=10.0.8.x -e WG_DEFAULT_DNS=114.114.114.114 -e WG_ALLOWED_IPS=0.0.0.0/0,::/0 -e WG_PERSISTENT_KEEPALIVE=25 -v ~/wg-easy:/etc/wireguard -p 51820:51820/udp -p 51821:51821/tcp --cap-add=NET_ADMIN --cap-add=SYS_MODULE --sysctl='net.ipv4.conf.all.src_valid_mark=1' --sysctl='net.ipv4.ip_forward=1' --restart unless-stopped ghcr.io/wg-easy/wg-easy\r\n\r\n```\r\n\r\n\ud83d\udc47\u5b89\u88c5\u6210\u529f\u540e\u8fd9\u91cc\u4f1a\u663e\u793a\u8fd0\u884c\u4e2d  \r\n![image.png](https://easyimage.01011205.xyz/i/0/2024/09/10/xfgj9l-0.png)\r\n\r\n\r\n\u4f7f\u7528IP+\u7aef\u53e351821\u767b\u9646  \r\n\u9ed8\u8ba4\u5bc6\u7801\u662f:passwd123  \r\n\u8fdb\u6765\u4e4b\u540e\u70b9\u51fb+\u53f7 \u521b\u5efa\u5ba2\u6237\u7aef  \r\n![image.png](https://easyimage.01011205.xyz/i/0/2024/09/10/xfhsea-0.png)\r\n\r\n\r\n\u63a5\u4e0b\u6765\u8981\u5728Lucky'Stun'\u628aWireGuard \u7aef\u53e351820/udp \u6253\u51fa\u516c\u7f51  \r\n![image.png](https://easyimage.01011205.xyz/i/0/2024/09/10/xfkimw-0.png)\r\n\r\n![image.png](https://easyimage.01011205.xyz/i/0/2024/09/10/xfw1zd-0.png)\r\n\r\n![image.png](https://easyimage.01011205.xyz/i/0/2024/09/10/xfy5x3-0.png)\r\n\r\n\u56fe\u7247\u4e2d3000\u5b9e\u9645\u662f30000\u4ee5\u4e0a  \r\n![image.png](https://easyimage.01011205.xyz/i/0/2024/09/10/xg1uml-0.png)\r\n\r\n![image.png](https://easyimage.01011205.xyz/i/0/2024/09/10/xg4fn4-0.png)\r\n\r\n\ud83d\udc47\u901a\u8fc7\u4e8c\u7ef4\u7801 \u626b\u63cfWireGuard\u8282\u70b9\u540e\u9700\u8981\u4fee\u6539IP\u548c\u7aef\u53e3  \r\n![image.png](https://easyimage.01011205.xyz/i/0/2024/09/10/xg6ju2-0.png)\r\n\r\n![image.png](https://easyimage.01011205.xyz/i/0/2024/09/10/xghbm4-0.png)\r\n\r\n\r\n## ----------\u4ee5\u4e0a\u6559\u7a0b\u4ee5\u5b8c\u621090%---------------  \r\nWebhook\r\n\r\n\u5173\u4e8eIP\u81ea\u52a8\u63a8\u9001\u53ef\u4ee5\u7528TG/\u9489\u9489\u7b49  \r\n\u53c2\u8003\u8fd9\u5f20\u56fe\u8bbe\u7f6e  \r\n![image.png](https://easyimage.01011205.xyz/i/0/2024/09/10/xgjogo-0.png)\r\n\r\n\r\n\u8bf7\u6c42\u4e3b\u4f53:\r\n\r\n```swift\r\n{\r\n    'msgtype': 'text',\r\n    'text': {\r\n        'content': '\u9489\u9489\u63a8\u9001 \\n #{time} \\n Home\u5f53\u524d\u516c\u7f51IP\\n#{ipAddr}'\r\n    }\r\n}\r\n```\r\n\r\n## ----------\u5b8c---------------\r\n\r\n### \u611f\u8c22\u5f00\u53d1\u8005:\r\n\r\n[iStoreOS\u56e2\u961f](https://www.istoreos.com/)  \r\n[Lucky\u4f5c\u8005\u53e4\u5927\u7f8a](https://github.com/gdy666/lucky)  \r\n[Github-wg-easy\u9879\u76ee](https://github.com/wg-easy/wg-easy)\r\n\r\n\u6587\u7ae0\u7f16\u5199:TheX\r\n\r\n\u8f6c\u8f7d\u81ea\uff1a\r\n# [\u3010\u56fe\u6587\u6559\u7a0b\u3011\u5bb6\u5bdb\u5b9e\u6218\u56de\u5bb6\u7bc7!\u4e4b:\u5229\u7528iStoreOS\u8f6f\u8def\u7531\u4f7f\u62e8\u53f7'\u65e0\u516c\u7f51IP'NAT1\u7f51\u7edc\u4e0b \u4e5f\u80fd\u83b7\u53d6\u5230'\u516c\u7f51IP+\u7aef\u53e3' ,\u642d\u5efaWireGuard\u670d\u52a1\u5668\u56de\u5bb6!](https://www.nodeseek.com/post-158404-1)\u00a0\u00a0\r\n\u3002", "top": 0, "createdAt": 1725971190, "style": "", "script": "", "head": "", "ogImage": "https://easyimage.01011205.xyz/i/2024/09/08/nlnmn5.png", "createdDate": "2024-09-10", "dateLabelColor": "#bc4c00"}, "P11": {"htmlDir": "docs/post/teng-xun-yun-DD-xi-tong-zui-jian-dan-de-fang-fa.html", "labels": ["documentation"], "postTitle": "\u817e\u8baf\u4e91DD\u7cfb\u7edf\u6700\u7b80\u5355\u7684\u65b9\u6cd5", "postUrl": "post/teng-xun-yun-DD-xi-tong-zui-jian-dan-de-fang-fa.html", "postSourceUrl": "https://github.com/samling-jackyjyo/samling-jackyjyo.github.io/issues/11", "commentNum": 0, "wordCount": 5947, "description": "\r\n### 1\u3001dd\u524d\u8fd0\u884c\u6e05\u7406\u76d1\u63a7\u6587\u4ef6\r\n\r\n\r\n```\r\n#!/bin/bash \r\n#fuck tx process \r\nrm -rf /usr/local/sa \r\nrm -rf /usr/local/agenttools \r\nrm -rf /usr/local/qcloud \r\nprocess=(sap100 secu-tcs-agent sgagent64 barad_agent agent agentPlugInD pvdriver ) \r\nfor i in ${process[@]} \r\ndo\r\nfor A in $(ps aux |grep $i |grep -v grep |awk '{print $2}') \r\ndo\r\nkill -9 $A \r\ndone \r\ndone \r\nchkconfig --level 35 postfix off \r\nservice postfix stop \r\necho ''>/var/spool/cron/root \r\necho '#!/bin/bash' >/etc/rc.local\r\n```\r\n\r\n### 2\u3001\u8fd0\u884c\u811a\u672c\r\n\r\n```\r\ncurl -O https://raw.githubusercontent.com/bin456789/reinstall/main/reinstall.sh\r\n```\r\n\r\n## \u529f\u80fd 1:\u5b89\u88c5Linux\r\n\r\n\r\n```\r\nbash reinstall.sh\r\n```\r\n\r\n- \u4e0d\u8f93\u5165\u7248\u672c\u53f7\uff0c\u5219\u5b89\u88c5\u6700\u65b0\u7248\r\n- \u4e0d\u542b boot \u5206\u533a\uff08Fedora \u4f8b\u5916\uff09\uff0c\u4e0d\u542b swap \u5206\u533a\uff0c\u6700\u5927\u5316\u5229\u7528\u78c1\u76d8\u7a7a\u95f4\r\n- \u5728\u865a\u62df\u673a\u4e0a\uff0c\u4f1a\u81ea\u52a8\u5b89\u88c5\u5408\u9002\u7684\u5b98\u65b9\u7cbe\u7b80\u5185\u6838\r\n- \u5b89\u88c5 Red Hat \u9700\u586b\u5199\u00a0[https://access.redhat.com/downloads/content/rhel](https://access.redhat.com/downloads/content/rhel)\u00a0\u5f97\u5230\u7684\u00a0`qcow2`\u00a0\u955c\u50cf\u94fe\u63a5\r\n- \u7528\u6237\u540d\u00a0`root`\u00a0\u5bc6\u7801\u00a0`123@@@`\uff0c\u53ef\u80fd\u9996\u6b21\u5f00\u673a\u51e0\u5206\u949f\u540e\u5bc6\u7801\u624d\u751f\u6548\r\n```\r\nbash reinstall.sh centos      9\r\n                  anolis      7|8\r\n                  alma        8|9\r\n                  rocky       8|9\r\n                  redhat      8|9   --img='http://xxx.com/xxx.qcow2'\r\n                  opencloudos 8|9\r\n                  oracle      7|8|9\r\n                  fedora      39|40\r\n                  nixos       24.05\r\n                  debian      9|10|11|12\r\n                  openeuler   20.03|22.03|24.03\r\n                  alpine      3.17|3.18|3.19|3.20\r\n                  opensuse    15.5|15.6|tumbleweed\r\n                  ubuntu      16.04|18.04|20.04|22.04|24.04 [--minimal]\r\n                  kali\r\n                  arch\r\n                  gentoo\r\n```\r\n\r\n\r\n## \u529f\u80fd 2: \u5b89\u88c5Windows ISO\r\n- \u7528\u6237\u540d\u00a0`administrator`\u00a0\u5bc6\u7801\u00a0`123@@@`\r\n- \u5982\u679c\u8fdc\u7a0b\u767b\u5f55\u5931\u8d25\uff0c\u5c1d\u8bd5\u4f7f\u7528\u7528\u6237\u540d\u00a0`.\\administrator`\r\n- \u9759\u6001\u673a\u5668\u4f1a\u81ea\u52a8\u914d\u7f6e\u597d IP\uff0c\u53ef\u80fd\u9996\u6b21\u5f00\u673a\u51e0\u5206\u949f\u540e\u624d\u751f\u6548\r\n\r\n#### \u65b9\u6cd5 1: \u8ba9\u811a\u672c\u81ea\u52a8\u67e5\u627e ISO\r\n\r\n[](https://github.com/bin456789/reinstall#%E6%96%B9%E6%B3%95-1-%E8%AE%A9%E8%84%9A%E6%9C%AC%E8%87%AA%E5%8A%A8%E6%9F%A5%E6%89%BE-iso)\r\n\r\n- \u811a\u672c\u4f1a\u4ece\u00a0[https://massgrave.dev/genuine-installation-media.html](https://massgrave.dev/genuine-installation-media.html)\u00a0\u67e5\u627e iso\uff0c\u8be5\u7f51\u7ad9\u63d0\u4f9b\u7684 iso \u90fd\u662f\u5b98\u65b9\u539f\u7248\r\n\r\n```shell\r\nbash reinstall.sh windows \\\r\n     --image-name 'Windows 10 Enterprise LTSC 2021' \\\r\n     --lang zh-cn\r\n```\r\n\r\n#### \u65b9\u6cd5 2: \u81ea\u884c\u6307\u5b9a ISO \u8fde\u63a5\r\n\r\n[](https://github.com/bin456789/reinstall#%E6%96%B9%E6%B3%95-2-%E8%87%AA%E8%A1%8C%E6%8C%87%E5%AE%9A-iso-%E8%BF%9E%E6%8E%A5)\r\n\r\n- \u5982\u679c\u4e0d\u77e5\u9053\u00a0`--image-name`\uff0c\u53ef\u4ee5\u968f\u4fbf\u586b\uff0c\u91cd\u542f\u540e\u8fde\u63a5 SSH \uff0c\u6839\u636e\u9519\u8bef\u63d0\u793a\u91cd\u65b0\u8f93\u5165\r\n\r\n```shell\r\nbash reinstall.sh windows \\\r\n     --image-name 'Windows 10 Enterprise LTSC 2021' \\\r\n     --iso 'https://drive.massgrave.dev/en-us_windows_10_enterprise_ltsc_2021_x64_dvd_d289cf96.iso'\r\n```\r\n\r\n\u4ee5\u4e0b\u7f51\u7ad9\u53ef\u627e\u5230 iso \u94fe\u63a5\r\n\r\n- [https://massgrave.dev/genuine-installation-media.html](https://massgrave.dev/genuine-installation-media.html)\u00a0(\u63a8\u8350\uff0ciso \u6765\u81ea\u5b98\u65b9\uff0c\u6bcf\u6708\u66f4\u65b0\uff0c\u5305\u542b\u6700\u65b0\u8865\u4e01)\r\n- [https://www.microsoft.com/software-download/windows10](https://www.microsoft.com/software-download/windows10)\u00a0(\u9700\u7528\u624b\u673a User-Agent \u6253\u5f00)\r\n- [https://www.microsoft.com/software-download/windows11](https://www.microsoft.com/software-download/windows11)\r\n- [https://www.microsoft.com/software-download/windowsinsiderpreviewiso](https://www.microsoft.com/software-download/windowsinsiderpreviewiso)\u00a0(\u9884\u89c8\u7248)\r\n- [https://www.microsoft.com/evalcenter/download-windows-10-enterprise](https://www.microsoft.com/evalcenter/download-windows-10-enterprise)\r\n- [https://www.microsoft.com/evalcenter/download-windows-11-enterprise](https://www.microsoft.com/evalcenter/download-windows-11-enterprise)\r\n- [https://www.microsoft.com/evalcenter/download-windows-11-iot-enterprise-ltsc](https://www.microsoft.com/evalcenter/download-windows-11-iot-enterprise-ltsc)\r\n- [https://www.microsoft.com/evalcenter/download-windows-server-2012-r2](https://www.microsoft.com/evalcenter/download-windows-server-2012-r2)\r\n- [https://www.microsoft.com/evalcenter/download-windows-server-2016](https://www.microsoft.com/evalcenter/download-windows-server-2016)\r\n- [https://www.microsoft.com/evalcenter/download-windows-server-2019](https://www.microsoft.com/evalcenter/download-windows-server-2019)\r\n- [https://www.microsoft.com/evalcenter/download-windows-server-2022](https://www.microsoft.com/evalcenter/download-windows-server-2022)\r\n- [https://www.microsoft.com/evalcenter/download-windows-server-2025](https://www.microsoft.com/evalcenter/download-windows-server-2025)\r\n\r\n![image](https://easyimage.01011205.xyz/i/2024/09/11/f689j4.png)\r\n\r\n\r\n#### \u53c2\u6570\u8bf4\u660e\r\n\r\n[](https://github.com/bin456789/reinstall?tab=readme-ov-file#%E5%8F%82%E6%95%B0%E8%AF%B4%E6%98%8E)\r\n\r\n`--image-name`\u00a0\u6307\u5b9a\u8981\u5b89\u88c5\u7684\u6620\u50cf\uff0c\u4e0d\u533a\u5206\u5927\u5c0f\u5199\uff0c\u5e38\u7528\u6620\u50cf\u6709\uff1a\r\n\r\n```\r\nWindows 7 Ultimate\r\nWindows 10 Enterprise LTSC 2021\r\nWindows 11 Pro\r\nWindows Server 2022 SERVERDATACENTER\r\n```\r\n\r\n\u4f7f\u7528\u00a0`Dism++`\u00a0\u6587\u4ef6\u83dc\u5355 > \u6253\u5f00\u6620\u50cf\u6587\u4ef6\uff0c\u9009\u62e9\u8981\u5b89\u88c5\u7684 iso\uff0c\u53ef\u4ee5\u5f97\u5230\u6620\u50cf\u540d\u79f0\r\n\r\n![image](https://easyimage.01011205.xyz/i/2024/09/11/f7yjnv.png)\r\n\r\n\r\n\r\n#### \u652f\u6301\u7684\u7cfb\u7edf\r\n\r\n[](https://github.com/bin456789/reinstall?tab=readme-ov-file#%E6%94%AF%E6%8C%81%E7%9A%84%E7%B3%BB%E7%BB%9F)\r\n\r\n- Windows (Vista ~ 11)\r\n- Windows Server (2008 ~ 2025)\r\n    - Windows Server Essentials *\r\n    - Windows Server (Semi) \u5e74\u5ea6\u9891\u9053 *\r\n    - \u00a0Hyper-V \u670d\u52a1\u5668 *\r\n    - Azure Stack HCI *\r\n\r\n* \u9700\u586b\u5199 iso \u94fe\u63a5\r\n\r\n#### \u811a\u672c\u4f1a\u6309\u9700\u5b89\u88c5\u4ee5\u4e0b\u9a71\u52a8\r\n\r\n[](https://github.com/bin456789/reinstall?tab=readme-ov-file#%E8%84%9A%E6%9C%AC%E4%BC%9A%E6%8C%89%E9%9C%80%E5%AE%89%E8%A3%85%E4%BB%A5%E4%B8%8B%E9%A9%B1%E5%8A%A8)\r\n\r\n- KVM ([Virtio](https://fedorapeople.org/groups/virt/virtio-win/direct-downloads/)\u3001[\u963f\u91cc\u4e91](https://www.alibabacloud.com/help/ecs/user-guide/update-red-hat-virtio-drivers-of-windows-instances))\r\n- XEN (XEN\u3001Citrix\u3001AWS)\r\n- AWS ([ENA \u7f51\u5361](https://docs.aws.amazon.com/AWSEC2/latest/UserGuide/ena-driver-releases-windows.html)\u3001[NVME \u5b58\u50a8\u63a7\u5236\u5668](https://docs.aws.amazon.com/AWSEC2/latest/UserGuide/nvme-driver-version-history.html))\r\n- GCP ([gVNIC \u7f51\u5361](https://cloud.google.com/compute/docs/networking/using-gvnic)\u3001[GGA \u663e\u5361](https://cloud.google.com/compute/docs/instances/enable-instance-virtual-display))\r\n- \u00a0Azure (MANA \u7f51\u5361)\r\n\r\n\u8f6c\u8f7d\u81ea\uff1a[https://github.com/bin456789/reinstall](https://github.com/bin456789/reinstall)\r\n\u3002", "top": 0, "createdAt": 1726054526, "style": "", "script": "", "head": "", "ogImage": "https://easyimage.01011205.xyz/i/2024/09/08/nlnmn5.png", "createdDate": "2024-09-11", "dateLabelColor": "#bc4c00"}, "P12": {"htmlDir": "docs/post/Docker -an-zhuang- rclone -gua-zai- Onedrive -dao-ben-di.html", "labels": ["documentation"], "postTitle": "Docker \u5b89\u88c5 rclone \u6302\u8f7d Onedrive \u5230\u672c\u5730", "postUrl": "post/Docker%20-an-zhuang-%20rclone%20-gua-zai-%20Onedrive%20-dao-ben-di.html", "postSourceUrl": "https://github.com/samling-jackyjyo/samling-jackyjyo.github.io/issues/12", "commentNum": 0, "wordCount": 2183, "description": "## \u4e00\u3001\u4e86\u89e3 rclone\r\n\r\n[rclone](https://www.amjun.com/tag/r/ '\u67e5\u770brclone\u7684\u6240\u6709\u6587\u7ae0')\u00a0\u662f\u4e00\u4e2a\u547d\u4ee4\u884c\u5de5\u5177\uff0c\u53ef\u4ee5\u7528\u6765\u7ba1\u7406\u5404\u79cd\u4e91\u5b58\u50a8\u670d\u52a1\u3002", "top": 0, "createdAt": 1726145320, "style": "", "script": "", "head": "", "ogImage": "https://easyimage.01011205.xyz/i/2024/09/08/nlnmn5.png", "createdDate": "2024-09-12", "dateLabelColor": "#bc4c00"}, "P13": {"htmlDir": "docs/post/2024-zui-xin-de-yi-jian-jiao-ben-da-jian-frp-nei-wang-chuan-tou-jiao-cheng.html", "labels": ["documentation"], "postTitle": "2024\u6700\u65b0\u7684\u4e00\u952e\u811a\u672c\u642d\u5efafrp\u5185\u7f51\u7a7f\u900f\u6559\u7a0b", "postUrl": "post/2024-zui-xin-de-yi-jian-jiao-ben-da-jian-frp-nei-wang-chuan-tou-jiao-cheng.html", "postSourceUrl": "https://github.com/samling-jackyjyo/samling-jackyjyo.github.io/issues/13", "commentNum": 0, "wordCount": 1494, "description": "\r\n1\u3001OpenWrt\u8f6f\u8def\u7531\u56fa\u4ef6\uff1a\u3010[\u70b9\u51fb\u8fdb\u5165](https://github.com/sirpdboy/openwrt#%E5%9B%BA%E4%BB%B6%E4%B8%8B%E8%BD%BD)\u3011\r\n\r\n- \u66f4\u591a\u56fa\u4ef6\u53ef\u53c2\u8003\u6b64\u6587\u7ae0\uff1a\u3010[\u70b9\u51fb\u8fdb\u5165](https://naiyous.com/2336.html)\u3011\r\n\r\n- SSH\u8fde\u63a5\u5de5\u5177Finalshell\uff1a\u3010[\u70b9\u51fb\u8fdb\u5165](https://www.hostbuf.com/t/988.html)\u3011\r\n\r\n2\u3001FRP\u5f00\u6e90\u9879\u76ee\u5730\u5740\uff1a\u3010[\u70b9\u51fb\u8fdb\u5165](https://github.com/fatedier/frp)\u3011\r\n\r\n3\u3001FRP\u4e00\u952e\u811a\u672c\u5730\u5740\uff1a\u3010[\u70b9\u51fb\u8fdb\u5165](https://github.com/MvsCode/frps-onekey?tab=readme-ov-file)\u3011\r\n\r\n- \u4e00\u952e\u5b89\u88c5\u811a\u672c\r\n\r\n```\r\nwget https://gitee.com/mvscode/frps-onekey/raw/master/install-frps.sh -O ./install-frps.sh\r\nchmod 700 ./install-frps.sh\r\n./install-frps.sh install\r\n```\r\n\r\n- \u8bbe\u7f6e\u540e\u53f0\u8fd0\u884c\r\n\r\n```\r\nnohup ./frps -c frps.ini >/dev/null 2>&1 &\r\n```\r\n\r\n- \u9632\u706b\u5899\u76f8\u5173\uff08==\u56fd\u5185\u670d\u52a1\u5668\u53ef\u4ee5\u76f4\u63a5\u8bbe\u7f6e\u9632\u706b\u5899\u89c4\u5219==\uff09\r\n\r\n```\r\nDebian\u6216Ubuntu\u7cfb\u7edf\u653e\u884c\u7aef\u53e3\uff1a\r\nufw allow \u7aef\u53e3\u53f7\r\niptables -A INPUT -p tcp --dport \u7aef\u53e3\u53f7 -j ACCEPT\r\n\r\nCentOS\u7cfb\u7edf\u653e\u884c\u7aef\u53e3\uff1a\r\nfirewall-cmd --zone=public --add-port=\u7aef\u53e3\u53f7/tcp --permanent\r\n```\r\n\r\n- FRP\u5e38\u7528\u547d\u4ee4\r\n\r\n```\r\n\u5f00\u542fFRP\uff1afrps start\r\n\r\n\u505c\u6b62FRP\uff1afrps stop\r\n\r\n\u91cd\u542fFRP\uff1afrps restart\r\n\r\n\u6253\u5f00\u914d\u7f6e\u6587\u4ef6\uff1afrps config\r\n\r\n\u67e5\u770bFRP\u7248\u672c\uff1afrps version\r\n\r\n\u68c0\u67e5FRP\u8fd0\u884c\u72b6\u6001\uff1afrps status\r\n```\r\n\r\n4\u3001openwrt\u8bbe\u7f6e\r\n\r\n- \u5b89\u88c5frpc\r\n    - frpc\u4e0b\u8f7d\uff1a\u3010[\u70b9\u51fb\u8fdb\u5165](https://github.com/kuoruan/openwrt-frp/releases)\u3011\r\n    - luci-app-frpc\u548c\u6c49\u5316\u5305\u4e0b\u8f7d\uff1a\u3010[\u70b9\u51fb\u8fdb\u5165](https://github.com/kuoruan/luci-app-frpc/releases)\u3011\r\n    - \u67e5\u770bCPU\u67b6\u6784\r\n\r\n```\r\ncat /etc/os-release |grep ARCH\r\n```\r\n\r\n- \u8bbe\u7f6e\r\n![image.png](https://easyimage.01011205.xyz/i/0/2024/09/17/wblrz3-0.png)\r\n\r\n![image.png](https://easyimage.01011205.xyz/i/0/2024/09/17/wbmpz1-0.png)\r\n\r\n\u8f6c\u8f7d\u81ea\uff1a[2024\u6700\u65b0\u7684\u4e00\u952e\u811a\u672c\u642d\u5efafrp\u5185\u7f51\u7a7f\u900f\uff0c\u5728\u5916\u8f7b\u677e\u8fdc\u7a0b\u8bbf\u95ee\u5185\u7f51\u8bbe\u5907|\u8fdc\u7a0b\u684c\u9762\uff01\u975e\u5e38\u7b80\u5355\u7684\u914d\u7f6e\u6d41\u7a0b\uff0c\u642d\u914dopenwrt\u8f6f\u8def\u7531\u6765\u4f7f\u7528\uff0c\u975e\u5e38\u597d\u7528\uff01windows\u914d\u7f6e#\u4e00\u74f6\u5976\u6cb9](https://naiyous.com/4482.html)\r\n\u3002", "top": 0, "createdAt": 1726574178, "style": "", "script": "", "head": "", "ogImage": "https://easyimage.01011205.xyz/i/2024/09/08/nlnmn5.png", "createdDate": "2024-09-17", "dateLabelColor": "#bc4c00"}, "P14": {"htmlDir": "docs/post/Debian -wo-de-chang-yong-yi-jian-jiao-ben.html", "labels": ["documentation"], "postTitle": "Debian \u6211\u7684\u5e38\u7528\u4e00\u952e\u811a\u672c", "postUrl": "post/Debian%20-wo-de-chang-yong-yi-jian-jiao-ben.html", "postSourceUrl": "https://github.com/samling-jackyjyo/samling-jackyjyo.github.io/issues/14", "commentNum": 0, "wordCount": 1293, "description": "\u840c\u5496\u5927\u4f6c\u4e00\u952eDD\u811a\u672c\r\n\u66f4\u65b0\r\n```\r\napt-get update\r\n```\r\n\r\n\u5b89\u88c5\u5fc5\u5907\u5de5\u5177\r\n```\r\napt-get install -y xz-utils openssl gawk file\r\n```\r\n\r\n\u5168\u81ea\u52a8\u4e00\u952e\u5b89\u88c5 debian 12\r\n```\r\nbash <(wget --no-check-certificate -qO- 'https://moeclub.org/attachment/LinuxShell/InstallNET.sh') -d 12 -v 64 -p \u767b\u5f55\u5bc6\u7801 -a\r\n\r\n```\r\n\u66f4\u591a\u53c2\u8003:https://github.com/Tasle/InstallNET\r\n\r\n\u4e00\u952e\u66f4\u65b0\u7cfb\u7edf\r\n```\r\napt update -y && apt full-upgrade -y && apt autoremove -y && apt autoclean -y\r\n```\r\n\r\n\u67e5\u770b Debian \u7248\u672c\r\n```\r\ncat /etc/debian_version\r\n```\r\n\r\n\u4e00\u952e\u5b89\u88c5 wget curl git\r\n```\r\napt install sudo curl wget \r\n\r\n```\r\n\r\n\u4e00\u952e\u66ff\u6362\u6700\u65b0\u5185\u6838 BBR (\u5378\u8f7d\u5185\u6838\u7248\u672c)\r\n```\r\nwget -O tcp.sh 'https://github.com/ylx2016/Linux-NetSpeed/raw/master/tcp.sh' && chmod +x tcp.sh && ./tcp.sh\r\n\r\n```\r\n\u6211\u4e00\u822c\u9009\u62e9 BBRplus 5 -> 19\r\n\u5f39\u51fa\u63d0\u793a\u9009\u62e9 NO\r\n\r\n\r\n\u4e00\u952e IP \u8d28\u91cf\u4f53\u68c0\u548c\u89e3\u9501\u68c0\u6d4b\r\n```\r\nbash <(curl -Ls IP.Check.Place)\r\n\r\n```\r\n\u878d\u5408\u602a\r\n```\r\ncurl -L https://gitlab.com/spiritysdx/za/-/raw/main/ecs.sh -o ecs.sh && chmod +x ecs.sh && bash ecs.sh\r\n\r\n```\r\n\r\n\u79d1\u6280lion\u811a\u672c\u5de5\u5177\u7bb1\r\n```\r\nbash <(curl -sL kejilion.sh)\r\n```\r\n\r\n\u6211\u4e00\u822c\u9009\u62e9\r\n13 -> 2 \u4fee\u6539\u767b\u5f55\u5bc6\u7801\r\n13 -> 6 \u4fee\u6539SSH\u8fde\u63a5\u7aef\u53e3\r\n13 -> 12 \u4fee\u6539\u865a\u62df\u5185\u5b58\u5927\u5c0f\r\n13 -> 15 \u7cfb\u7edf\u65f6\u533a\u8c03\u6574\r\n13 -> 22 fail2banSSH\u9632\u5fa1\u7a0b\u5e8f\r\n13 -> 26 \u4fee\u590dOpenSSH\u9ad8\u5371\u6f0f\u6d1e\uff08\u5cab\u6e90\uff09\r\n\r\n\r\n\u53c2\u8003\u8d44\u6599 [2024\u5e74\u6700\u5168\u9762VPS\u8c03\u4f18\u6559\u7a0b](https://www.youtube.com/watch?v=OR73PNaJmbk)\r\n\r\n\u5b89\u88c5 Docker\r\n```\r\nhttps://igeekbb.com/2023/04/20/DockerCompose/\r\n```\r\n\r\n\u8f6c\u8f7d\u81ea\uff1a[Geek\u5927\u4f6c\u7684Debian \u6211\u7684\u5e38\u7528\u4e00\u952e\u811a\u672c]\uff08https://www.igeekbb.com/2024/09/18/debian/\uff09\u3002", "top": 0, "createdAt": 1727588699, "style": "", "script": "", "head": "", "ogImage": "https://easyimage.01011205.xyz/i/2024/09/08/nlnmn5.png", "createdDate": "2024-09-29", "dateLabelColor": "#bc4c00"}, "P15": {"htmlDir": "docs/post/zai-Serv00-shang-da-jian-FreshRSS.html", "labels": ["documentation"], "postTitle": "\u5728Serv00\u4e0a\u642d\u5efaFreshRSS", "postUrl": "post/zai-Serv00-shang-da-jian-FreshRSS.html", "postSourceUrl": "https://github.com/samling-jackyjyo/samling-jackyjyo.github.io/issues/15", "commentNum": 0, "wordCount": 1987, "description": "\u8fd9\u4e2a\u975e\u5e38\u7b80\u5355\u554a\uff0c\u51e0\u6b65\u5c31\u5b8c\u6210\u4e86\r\n\r\n# [](https://linux.do/t/topic/220086#p-1965202-h-1serv00-1)1. \u5c06\u57df\u540d\u6258\u7ba1\u5230 serv00\r\n\r\n![image.png](https://easyimage.01011205.xyz/i/0/2024/09/30/dqdiyu-0.webp)\r\n\r\n\r\n\u53ef\u4ee5\u901a\u8fc7\u56de\u6e90\u65b9\u5f0f\u89e3\u51b3 IP \u88ab\u5899\u95ee\u9898  \r\n\u53c2\u8003\uff1a\r\n\r\n![](https://linux.do/user_avatar/linux.do/xjfkkk/48/12365_2.png)\u00a0[\u7ed9 serv00 \u6dfb\u52a0\u4f18\u8d28\u57df\u540d\u5e76\u52a0\u901f\u7f51\u7ad9](https://linux.do/t/topic/174317)\u00a0[\u8d44\u6e90\u835f\u8403](https://linux.do/c/resource/14)\r\n\r\n> serv00 \u4e0d\u52a0\u901f\u7f51\u7ad9\u7684\u60c5\u51b5\u4e0b\u5ef6\u8fdf\u6bd4\u8f83\u9ad8\uff0c\u800c\u4e14\u81ea\u5e26\u7684\u57df\u540d\u4e5f\u5f88\u4e0d\u7f8e\u89c2\u3002", "top": 0, "createdAt": 1727656829, "style": "", "script": "", "head": "", "ogImage": "https://easyimage.01011205.xyz/i/2024/09/08/nlnmn5.png", "createdDate": "2024-09-30", "dateLabelColor": "#bc4c00"}}, "singeListJson": {}, "labelColorDict": {"bug": "#d73a4a", "documentation": "#0075ca", "duplicate": "#cfd3d7", "enhancement": "#a2eeef", "good first issue": "#7057ff", "help wanted": "#008672", "invalid": "#e4e669", "question": "#d876e3", "wontfix": "#ffffff"}, "displayTitle": "\u571f\u62e8\u9f20\u7684\u535a\u5ba2", "faviconUrl": "https://easyimage.01011205.xyz/i/2024/09/08/nlnmn5.png", "ogImage": "https://easyimage.01011205.xyz/i/2024/09/08/nlnmn5.png", "primerCSS": "<link href='https://mirrors.sustech.edu.cn/cdnjs/ajax/libs/Primer/21.0.7/primer.css' rel='stylesheet' />", "homeUrl": "https://samling-jackyjyo.github.io", "prevUrl": "disabled", "nextUrl": "disabled"}